<nudsHoard xmlns="http://nomisma.org/nudsHoard" xmlns:mods="http://www.loc.gov/mods/v3" xmlns:nuds="http://nomisma.org/nuds" xmlns:gml="http://www.opengis.net/gml" xmlns:xsi="http://www.w3.org/2001/XMLSchema-instance" xmlns:xlink="http://www.w3.org/1999/xlink">
    <control>
        <recordId>igch0479</recordId>
        <maintenanceStatus>derived</maintenanceStatus>
        <publicationStatus>approved</publicationStatus>
        <maintenanceAgency>
            <agencyName>American Numismatic Society</agencyName>
        </maintenanceAgency>
        <maintenanceHistory>
            <maintenanceEvent>
                <eventType>derived</eventType>
                <eventDateTime standardDateTime="2020-04-17T19:35:50-04:00">Fri, 17 Apr 2020 19:35:50 -0400</eventDateTime>
                <agentType>human</agentType>
                <agent>Ethan Gruber</agent>
                <eventDescription>NUDS-Hoard records generated by Ethan Gruber from spreadsheets Disnarda Pinilla cleaned from the IGCH records.s</eventDescription>
            </maintenanceEvent>
        </maintenanceHistory>
        <rightsStmt>
            <copyrightHolder>American Numismatic Society</copyrightHolder>
            <license>http://opendatacommons.org/licenses/odbl/</license>
        </rightsStmt>
    </control>
    <descMeta>
        <title xml:lang="en">IGCH 479</title>
        <noteSet>
            <note>Possibly part of no. 481 below</note>
        </noteSet>
        <subjectSet>
            <subject localType="period" xlink:type="simple" xlink:href="http://nomisma.org/id/hellenistic_greece">Hellenistic Period</subject>
        </subjectSet>
        <hoardDesc>
            <findspot>
                <description xml:lang="en">Beroea, Macedonia</description>
                <fallsWithin>
                    <gml:location>
                        <gml:Point>
                            <gml:coordinates>22.20242,40.52437</gml:coordinates>
                        </gml:Point>
                    </gml:location>
                    <geogname xlink:type="simple" xlink:role="findspot" xlink:href="https://sws.geonames.org/733905/">Véroia (Greece)</geogname>
                    <geogname xlink:type="simple" xlink:role="ancient_place" xlink:href="https://pleiades.stoa.org/places/491546">Ber(r)oia</geogname>
                    <type xlink:type="simple" xlink:href="http://vocab.getty.edu/aat/300008347">inhabited places</type>
                </fallsWithin>
            </findspot>
            <deposit>
                <date standardDate="-0160">160 B.C.</date>
            </deposit>
            <discovery>
                <date standardDate="1962">1962</date>
            </discovery>
            <disposition>
                <description xml:lang="en">Athens</description>
            </disposition>
        </hoardDesc>
        <contentsDesc>
            <contents count="5">
                <description xml:lang="en">5 AR</description>
                <coin>
                    <nuds:typeDesc>
                        <nuds:denomination xlink:type="simple" xlink:href="http://nomisma.org/id/tetradrachm">Tetradrachm</nuds:denomination>
                        <nuds:material xlink:type="simple" xlink:href="http://nomisma.org/id/ar">Silver</nuds:material>
                        <nuds:geographic>
                            <nuds:geogname xlink:type="simple" xlink:role="mint" xlink:href="http://nomisma.org/id/thasos">Thasos</nuds:geogname>
                        </nuds:geographic>
                    </nuds:typeDesc>
                </coin>
                <coinGrp count="4">
                    <nuds:typeDesc>
                        <nuds:denomination xlink:type="simple" xlink:href="http://nomisma.org/id/tetradrachm">Tetradrachm</nuds:denomination>
                        <nuds:material xlink:type="simple" xlink:href="http://nomisma.org/id/ar">Silver</nuds:material>
                        <nuds:geographic>
                            <nuds:geogname xlink:type="simple" xlink:role="mint" xlink:href="http://nomisma.org/id/athens">Athens</nuds:geogname>
                        </nuds:geographic>
                    </nuds:typeDesc>
                </coinGrp>
            </contents>
        </contentsDesc>
        <refDesc>
            <reference>Varoucha, A Delt 1963, Chronika, p. 4, illus.</reference>
            <reference>Thompson, ANSMN 12 (1966), p. 60</reference>
        </refDesc>
    </descMeta>
</nudsHoard>