<?xml version="1.0" encoding="UTF-8"?>
<nudsHoard xmlns="http://nomisma.org/nudsHoard" xmlns:mods="http://www.loc.gov/mods/v3"
           xmlns:nuds="http://nomisma.org/nuds"
           xmlns:gml="http://www.opengis.net/gml"
           xmlns:xsi="http://www.w3.org/2001/XMLSchema-instance"
           xmlns:xlink="http://www.w3.org/1999/xlink">
   <recordId>igch0179</recordId>
   <maintenanceStatus>derived</maintenanceStatus>
   <publicationStatus>approved</publicationStatus>
   <maintenanceAgency>
      <agencyName>American Numismatic Society</agencyName>
   </maintenanceAgency>
   <maintenanceHistory>
      <maintenanceEvent>
         <eventType>derived</eventType>
         <eventDateTime standardDateTime="2020-04-17T19:35:07-04:00">Fri, 17 Apr 2020 19:35:07 -0400</eventDateTime>
         <agentType>human</agentType>
         <agent>Ethan Gruber</agent>
         <eventDescription>NUDS-Hoard records generated by Ethan Gruber from spreadsheets Disnarda Pinilla cleaned from the IGCH records.s</eventDescription>
      </maintenanceEvent>
   </maintenanceHistory>
   <rightsStmt>
      <copyrightHolder>American Numismatic Society</copyrightHolder>
      <license>http://opendatacommons.org/licenses/odbl/</license>
   </rightsStmt>
   <semanticDeclaration>
      <prefix>skos</prefix>
      <namespace>http://www.w3.org/2004/02/skos/core#</namespace>
   </semanticDeclaration>
   <semanticDeclaration>
      <prefix>dcterms</prefix>
      <namespace>http://purl.org/dc/terms/</namespace>
   </semanticDeclaration>
   <title xml:lang="en">IGCH 179</title>
   <noteSet>
      <note>* Six were subsequently analyzed and are no longer in the Athens collection</note>
      <note>** The record of Seleucid issues derives from  Newell's ESM and WSM and differs from those of Svoronos and Hackens</note>
   </noteSet>
   <subjectSet>
      <subject localType="period" xlink:type="simple"
               xlink:href="http://nomisma.org/id/hellenistic_greece">Hellenistic Period</subject>
   </subjectSet>
   <hoardDesc>
      <findspot>
         <description xml:lang="en">Sophikon, N of Epidaurus, Argolis</description>
         <fallsWithin>
            <gml:location>
               <gml:Point>
                  <gml:coordinates>23.05204,37.79412</gml:coordinates>
               </gml:Point>
            </gml:location>
            <geogname xlink:type="simple" xlink:role="findspot"
                      xlink:href="https://sws.geonames.org/253494/">Sofiko (Greece)</geogname>
            <type xlink:type="simple" xlink:href="http://vocab.getty.edu/aat/300008347">inhabited places</type>
         </fallsWithin>
      </findspot>
      <deposit>
         <dateRange>
            <fromDate standardDate="-0230">230 B.C.</fromDate>
            <toDate standardDate="-0220">220 B.C.</toDate>
         </dateRange>
      </deposit>
      <discovery>
         <date standardDate="1893">1893</date>
      </discovery>
      <disposition>
         <description xml:lang="en">Athens</description>
      </disposition>
   </hoardDesc>
   <contentsDesc>
      <contents count="950">
         <description xml:lang="en">c. 950 AR: 947 coins noted in IGCH. Added 3 coins to the hoard contents. Then, the total count comes to c. 950 coins</description>
         <coin>
            <nuds:typeDesc>
               <nuds:dateRange>
                  <nuds:fromDate standardDate="-0323">323 B.C.</nuds:fromDate>
                  <nuds:toDate standardDate="-0250">250 B.C.</nuds:toDate>
               </nuds:dateRange>
               <nuds:denomination xlink:type="simple" xlink:href="http://nomisma.org/id/tetradrachm">Tetradrachm</nuds:denomination>
               <nuds:material xlink:type="simple" xlink:href="http://nomisma.org/id/ar">Silver</nuds:material>
               <nuds:authority>
                  <nuds:persname xlink:type="simple" xlink:role="authority"
                                 xlink:href="http://nomisma.org/id/alexander_iii">Alexander III of Macedon</nuds:persname>
               </nuds:authority>
               <nuds:geographic>
                  <nuds:geogname xlink:type="simple" xlink:role="mint"
                                 xlink:href="http://nomisma.org/id/pella_macedon">Pella</nuds:geogname>
               </nuds:geographic>
            </nuds:typeDesc>
         </coin>
         <coin>
            <nuds:typeDesc>
               <nuds:dateRange>
                  <nuds:fromDate standardDate="-0323">323 B.C.</nuds:fromDate>
                  <nuds:toDate standardDate="-0250">250 B.C.</nuds:toDate>
               </nuds:dateRange>
               <nuds:denomination xlink:type="simple" xlink:href="http://nomisma.org/id/tetradrachm">Tetradrachm</nuds:denomination>
               <nuds:material xlink:type="simple" xlink:href="http://nomisma.org/id/ar">Silver</nuds:material>
               <nuds:authority>
                  <nuds:persname xlink:type="simple" xlink:role="authority"
                                 xlink:href="http://nomisma.org/id/alexander_iii">Alexander III of Macedon</nuds:persname>
               </nuds:authority>
               <nuds:geographic>
                  <nuds:geogname xlink:type="simple" xlink:role="mint"
                                 xlink:href="http://nomisma.org/id/megalopolis">Megalopolis</nuds:geogname>
               </nuds:geographic>
            </nuds:typeDesc>
         </coin>
         <coin>
            <nuds:typeDesc>
               <nuds:dateRange>
                  <nuds:fromDate standardDate="-0323">323 B.C.</nuds:fromDate>
                  <nuds:toDate standardDate="-0250">250 B.C.</nuds:toDate>
               </nuds:dateRange>
               <nuds:denomination xlink:type="simple" xlink:href="http://nomisma.org/id/tetradrachm">Tetradrachm</nuds:denomination>
               <nuds:material xlink:type="simple" xlink:href="http://nomisma.org/id/ar">Silver</nuds:material>
               <nuds:authority>
                  <nuds:persname xlink:type="simple" xlink:role="authority"
                                 xlink:href="http://nomisma.org/id/alexander_iii">Alexander III of Macedon</nuds:persname>
               </nuds:authority>
               <nuds:geographic>
                  <nuds:geogname xlink:type="simple" xlink:role="region"
                                 xlink:href="http://nomisma.org/id/peloponnesus"
                                 certainty="http://nomisma.org/id/uncertain_value">Peloponnesus</nuds:geogname>
               </nuds:geographic>
            </nuds:typeDesc>
         </coin>
         <coin>
            <nuds:typeDesc>
               <nuds:dateRange>
                  <nuds:fromDate standardDate="-0323">323 B.C.</nuds:fromDate>
                  <nuds:toDate standardDate="-0250">250 B.C.</nuds:toDate>
               </nuds:dateRange>
               <nuds:denomination xlink:type="simple" xlink:href="http://nomisma.org/id/tetradrachm">Tetradrachm</nuds:denomination>
               <nuds:material xlink:type="simple" xlink:href="http://nomisma.org/id/ar">Silver</nuds:material>
               <nuds:authority>
                  <nuds:persname xlink:type="simple" xlink:role="authority"
                                 xlink:href="http://nomisma.org/id/alexander_iii">Alexander III of Macedon</nuds:persname>
               </nuds:authority>
               <nuds:geographic>
                  <nuds:geogname xlink:type="simple" xlink:role="mint"
                                 xlink:href="http://nomisma.org/id/ephesus">Ephesus</nuds:geogname>
               </nuds:geographic>
            </nuds:typeDesc>
         </coin>
         <coinGrp count="4">
            <nuds:typeDesc>
               <nuds:dateRange>
                  <nuds:fromDate standardDate="-0323">323 B.C.</nuds:fromDate>
                  <nuds:toDate standardDate="-0250">250 B.C.</nuds:toDate>
               </nuds:dateRange>
               <nuds:denomination xlink:type="simple" xlink:href="http://nomisma.org/id/tetradrachm">Tetradrachm</nuds:denomination>
               <nuds:material xlink:type="simple" xlink:href="http://nomisma.org/id/ar">Silver</nuds:material>
               <nuds:authority>
                  <nuds:persname xlink:type="simple" xlink:role="authority"
                                 xlink:href="http://nomisma.org/id/alexander_iii">Alexander III of Macedon</nuds:persname>
               </nuds:authority>
               <nuds:geographic>
                  <nuds:geogname xlink:type="simple" xlink:role="mint" xlink:href="http://nomisma.org/id/aradus">Aradus</nuds:geogname>
               </nuds:geographic>
            </nuds:typeDesc>
         </coinGrp>
         <coin>
            <nuds:typeDesc>
               <nuds:dateRange>
                  <nuds:fromDate standardDate="-0323">323 B.C.</nuds:fromDate>
                  <nuds:toDate standardDate="-0250">250 B.C.</nuds:toDate>
               </nuds:dateRange>
               <nuds:denomination xlink:type="simple" xlink:href="http://nomisma.org/id/tetradrachm">Tetradrachm</nuds:denomination>
               <nuds:material xlink:type="simple" xlink:href="http://nomisma.org/id/ar">Silver</nuds:material>
               <nuds:authority>
                  <nuds:persname xlink:type="simple" xlink:role="authority"
                                 xlink:href="http://nomisma.org/id/alexander_iii">Alexander III of Macedon</nuds:persname>
               </nuds:authority>
               <nuds:geographic>
                  <nuds:geogname xlink:type="simple" xlink:role="mint"
                                 xlink:href="http://nomisma.org/id/ace_ptolemais">Ptolemais-Ake</nuds:geogname>
               </nuds:geographic>
            </nuds:typeDesc>
         </coin>
         <coin>
            <nuds:typeDesc>
               <nuds:dateRange>
                  <nuds:fromDate standardDate="-0323">323 B.C.</nuds:fromDate>
                  <nuds:toDate standardDate="-0250">250 B.C.</nuds:toDate>
               </nuds:dateRange>
               <nuds:denomination xlink:type="simple" xlink:href="http://nomisma.org/id/tetradrachm">Tetradrachm</nuds:denomination>
               <nuds:material xlink:type="simple" xlink:href="http://nomisma.org/id/ar">Silver</nuds:material>
               <nuds:authority>
                  <nuds:persname xlink:type="simple" xlink:role="authority"
                                 xlink:href="http://nomisma.org/id/alexander_iii">Alexander III of Macedon</nuds:persname>
               </nuds:authority>
               <nuds:geographic>
                  <nuds:geogname xlink:type="simple" xlink:role="mint"
                                 xlink:href="http://nomisma.org/id/babylon">Babylon</nuds:geogname>
               </nuds:geographic>
            </nuds:typeDesc>
         </coin>
         <coinGrp count="7">
            <nuds:typeDesc>
               <nuds:dateRange>
                  <nuds:fromDate standardDate="-0323">323 B.C.</nuds:fromDate>
                  <nuds:toDate standardDate="-0250">250 B.C.</nuds:toDate>
               </nuds:dateRange>
               <nuds:material xlink:type="simple" xlink:href="http://nomisma.org/id/ar">Silver</nuds:material>
               <nuds:authority>
                  <nuds:persname xlink:type="simple" xlink:role="authority"
                                 xlink:href="http://nomisma.org/id/alexander_iii">Alexander III of Macedon</nuds:persname>
               </nuds:authority>
            </nuds:typeDesc>
            <nuds:refDesc>
               <nuds:reference>illegible</nuds:reference>
            </nuds:refDesc>
         </coinGrp>
         <coinGrp count="702">
            <nuds:typeDesc>
               <nuds:dateRange>
                  <nuds:fromDate standardDate="-0336">336 B.C.</nuds:fromDate>
                  <nuds:toDate standardDate="-0323">323 B.C.</nuds:toDate>
               </nuds:dateRange>
               <nuds:denomination xlink:type="simple" xlink:href="http://nomisma.org/id/drachma">Drachma</nuds:denomination>
               <nuds:material xlink:type="simple" xlink:href="http://nomisma.org/id/ar">Silver</nuds:material>
               <nuds:authority>
                  <nuds:persname xlink:type="simple" xlink:role="authority"
                                 xlink:href="http://nomisma.org/id/alexander_iii">Alexander III of Macedon</nuds:persname>
               </nuds:authority>
               <nuds:geographic>
                  <nuds:geogname xlink:type="simple" xlink:role="region"
                                 xlink:href="http://nomisma.org/id/asia_minor">Asia Minor</nuds:geogname>
               </nuds:geographic>
            </nuds:typeDesc>
         </coinGrp>
         <coin>
            <nuds:typeDesc>
               <nuds:dateRange>
                  <nuds:fromDate standardDate="-0323">323 B.C.</nuds:fromDate>
                  <nuds:toDate standardDate="-0317">317 B.C.</nuds:toDate>
               </nuds:dateRange>
               <nuds:denomination xlink:type="simple" xlink:href="http://nomisma.org/id/tetradrachm">Tetradrachm</nuds:denomination>
               <nuds:material xlink:type="simple" xlink:href="http://nomisma.org/id/ar">Silver</nuds:material>
               <nuds:authority>
                  <nuds:persname xlink:type="simple" xlink:role="authority"
                                 xlink:href="http://nomisma.org/id/philip_iii_arrhidaeus">Philip III Arrhidaeus</nuds:persname>
               </nuds:authority>
               <nuds:geographic>
                  <nuds:geogname xlink:type="simple" xlink:role="mint"
                                 xlink:href="http://nomisma.org/id/babylon">Babylon</nuds:geogname>
               </nuds:geographic>
            </nuds:typeDesc>
         </coin>
         <coinGrp count="29">
            <nuds:typeDesc>
               <nuds:dateRange>
                  <nuds:fromDate standardDate="-0323">323 B.C.</nuds:fromDate>
                  <nuds:toDate standardDate="-0317">317 B.C.</nuds:toDate>
               </nuds:dateRange>
               <nuds:denomination xlink:type="simple" xlink:href="http://nomisma.org/id/drachma">Drachma</nuds:denomination>
               <nuds:material xlink:type="simple" xlink:href="http://nomisma.org/id/ar">Silver</nuds:material>
               <nuds:authority>
                  <nuds:persname xlink:type="simple" xlink:role="authority"
                                 xlink:href="http://nomisma.org/id/philip_iii_arrhidaeus">Philip III Arrhidaeus</nuds:persname>
               </nuds:authority>
               <nuds:geographic>
                  <nuds:geogname xlink:type="simple" xlink:role="region"
                                 xlink:href="http://nomisma.org/id/asia_minor">Asia Minor</nuds:geogname>
               </nuds:geographic>
            </nuds:typeDesc>
         </coinGrp>
         <coinGrp count="5">
            <nuds:typeDesc>
               <nuds:dateRange>
                  <nuds:fromDate standardDate="-0294">294 B.C.</nuds:fromDate>
                  <nuds:toDate standardDate="-0288">288 B.C.</nuds:toDate>
               </nuds:dateRange>
               <nuds:denomination xlink:type="simple" xlink:href="http://nomisma.org/id/drachma">Drachma</nuds:denomination>
               <nuds:material xlink:type="simple" xlink:href="http://nomisma.org/id/ar">Silver</nuds:material>
               <nuds:authority>
                  <nuds:persname xlink:type="simple" xlink:role="authority"
                                 xlink:href="http://nomisma.org/id/demetrius_i">Demetrius I Poliorcetes</nuds:persname>
               </nuds:authority>
            </nuds:typeDesc>
         </coinGrp>
         <coin>
            <nuds:typeDesc>
               <nuds:dateRange>
                  <nuds:fromDate standardDate="-0294">294 B.C.</nuds:fromDate>
                  <nuds:toDate standardDate="-0288">288 B.C.</nuds:toDate>
               </nuds:dateRange>
               <nuds:denomination xlink:type="simple" xlink:href="http://nomisma.org/id/triobol">Triobol</nuds:denomination>
               <nuds:material xlink:type="simple" xlink:href="http://nomisma.org/id/ar">Silver</nuds:material>
               <nuds:authority>
                  <nuds:persname xlink:type="simple" xlink:role="authority"
                                 xlink:href="http://nomisma.org/id/demetrius_i">Demetrius I Poliorcetes</nuds:persname>
               </nuds:authority>
               <nuds:geographic>
                  <nuds:geogname xlink:type="simple" xlink:role="mint"
                                 xlink:href="http://nomisma.org/id/ephesus"
                                 certainty="http://nomisma.org/id/uncertain_value">Ephesus</nuds:geogname>
                  <nuds:geogname xlink:type="simple" xlink:role="mint" xlink:href="http://nomisma.org/id/tarsus"
                                 certainty="http://nomisma.org/id/uncertain_value">Tarsus</nuds:geogname>
               </nuds:geographic>
            </nuds:typeDesc>
         </coin>
         <coinGrp count="3">
            <nuds:typeDesc>
               <nuds:dateRange>
                  <nuds:fromDate standardDate="-0277">277 B.C.</nuds:fromDate>
                  <nuds:toDate standardDate="-0239">239 B.C.</nuds:toDate>
               </nuds:dateRange>
               <nuds:denomination xlink:type="simple" xlink:href="http://nomisma.org/id/drachma">Drachma</nuds:denomination>
               <nuds:material xlink:type="simple" xlink:href="http://nomisma.org/id/ar">Silver</nuds:material>
               <nuds:authority>
                  <nuds:persname xlink:type="simple" xlink:role="authority"
                                 xlink:href="http://nomisma.org/id/antigonus_ii">Antigonus II Gonatas</nuds:persname>
               </nuds:authority>
            </nuds:typeDesc>
         </coinGrp>
         <coin>
            <nuds:typeDesc>
               <nuds:dateRange>
                  <nuds:fromDate standardDate="-0306">306 B.C.</nuds:fromDate>
                  <nuds:toDate standardDate="-0281">281 B.C.</nuds:toDate>
               </nuds:dateRange>
               <nuds:denomination xlink:type="simple" xlink:href="http://nomisma.org/id/tetradrachm">Tetradrachm</nuds:denomination>
               <nuds:material xlink:type="simple" xlink:href="http://nomisma.org/id/ar">Silver</nuds:material>
               <nuds:authority>
                  <nuds:persname xlink:type="simple" xlink:role="authority"
                                 xlink:href="http://nomisma.org/id/lysimachus">Lysimachus</nuds:persname>
               </nuds:authority>
            </nuds:typeDesc>
            <nuds:refDesc>
               <nuds:reference>illegible</nuds:reference>
            </nuds:refDesc>
         </coin>
         <coinGrp count="17">
            <nuds:typeDesc>
               <nuds:dateRange>
                  <nuds:fromDate standardDate="-0306">306 B.C.</nuds:fromDate>
                  <nuds:toDate standardDate="-0281">281 B.C.</nuds:toDate>
               </nuds:dateRange>
               <nuds:denomination xlink:type="simple" xlink:href="http://nomisma.org/id/drachma">Drachma</nuds:denomination>
               <nuds:material xlink:type="simple" xlink:href="http://nomisma.org/id/ar">Silver</nuds:material>
               <nuds:authority>
                  <nuds:persname xlink:type="simple" xlink:role="authority"
                                 xlink:href="http://nomisma.org/id/lysimachus">Lysimachus</nuds:persname>
               </nuds:authority>
            </nuds:typeDesc>
         </coinGrp>
         <coin>
            <nuds:typeDesc>
               <nuds:denomination xlink:type="simple" xlink:href="http://nomisma.org/id/tetradrachm">Tetradrachm</nuds:denomination>
               <nuds:material xlink:type="simple" xlink:href="http://nomisma.org/id/ar">Silver</nuds:material>
               <nuds:geographic>
                  <nuds:geogname xlink:type="simple" xlink:role="region"
                                 xlink:href="http://nomisma.org/id/aetolia">Aetolia</nuds:geogname>
               </nuds:geographic>
            </nuds:typeDesc>
         </coin>
         <coin>
            <nuds:typeDesc>
               <nuds:denomination xlink:type="simple" xlink:href="http://nomisma.org/id/tetradrachm">Tetradrachm</nuds:denomination>
               <nuds:material xlink:type="simple" xlink:href="http://nomisma.org/id/ar">Silver</nuds:material>
               <nuds:geographic>
                  <nuds:geogname xlink:type="simple" xlink:role="region"
                                 xlink:href="http://nomisma.org/id/boeotia">Boeotia</nuds:geogname>
               </nuds:geographic>
            </nuds:typeDesc>
         </coin>
         <coinGrp count="141">
            <nuds:typeDesc>
               <nuds:denomination xlink:type="simple" xlink:href="http://nomisma.org/id/tetradrachm">Tetradrachm</nuds:denomination>
               <nuds:material xlink:type="simple" xlink:href="http://nomisma.org/id/ar">Silver</nuds:material>
               <nuds:geographic>
                  <nuds:geogname xlink:type="simple" xlink:role="mint" xlink:href="http://nomisma.org/id/athens">Athens</nuds:geogname>
               </nuds:geographic>
            </nuds:typeDesc>
         </coinGrp>
         <coin>
            <nuds:typeDesc>
               <nuds:denomination xlink:type="simple" xlink:href="http://nomisma.org/id/tetradrachm">Tetradrachm</nuds:denomination>
               <nuds:material xlink:type="simple" xlink:href="http://nomisma.org/id/ar">Silver</nuds:material>
               <nuds:geographic>
                  <nuds:geogname xlink:type="simple" xlink:role="mint"
                                 xlink:href="http://nomisma.org/id/lacedaemon">Lacedaemon</nuds:geogname>
               </nuds:geographic>
            </nuds:typeDesc>
         </coin>
         <coin>
            <nuds:typeDesc>
               <nuds:dateRange>
                  <nuds:fromDate standardDate="-0241">241 B.C.</nuds:fromDate>
                  <nuds:toDate standardDate="-0197">197 B.C.</nuds:toDate>
               </nuds:dateRange>
               <nuds:denomination xlink:type="simple" xlink:href="http://nomisma.org/id/tetradrachm">Tetradrachm</nuds:denomination>
               <nuds:material xlink:type="simple" xlink:href="http://nomisma.org/id/ar">Silver</nuds:material>
               <nuds:authority>
                  <nuds:persname xlink:type="simple" xlink:role="authority"
                                 xlink:href="http://nomisma.org/id/attalus_i">Attalus I</nuds:persname>
               </nuds:authority>
            </nuds:typeDesc>
         </coin>
         <coinGrp count="2">
            <nuds:typeDesc>
               <nuds:denomination xlink:type="simple" xlink:href="http://nomisma.org/id/drachma">Drachma</nuds:denomination>
               <nuds:material xlink:type="simple" xlink:href="http://nomisma.org/id/ar">Silver</nuds:material>
               <nuds:geographic>
                  <nuds:geogname xlink:type="simple" xlink:role="mint" xlink:href="http://nomisma.org/id/rhodes">Rhodes</nuds:geogname>
               </nuds:geographic>
            </nuds:typeDesc>
         </coinGrp>
         <coin>
            <nuds:typeDesc>
               <nuds:dateRange>
                  <nuds:fromDate standardDate="-0305">305 B.C.</nuds:fromDate>
                  <nuds:toDate standardDate="-0281">281 B.C.</nuds:toDate>
               </nuds:dateRange>
               <nuds:denomination xlink:type="simple" xlink:href="http://nomisma.org/id/tetradrachm">Tetradrachm</nuds:denomination>
               <nuds:material xlink:type="simple" xlink:href="http://nomisma.org/id/ar">Silver</nuds:material>
               <nuds:authority>
                  <nuds:persname xlink:type="simple" xlink:role="authority"
                                 xlink:href="http://nomisma.org/id/seleucus_i">Seleucus I Nicator</nuds:persname>
               </nuds:authority>
               <nuds:geographic>
                  <nuds:geogname xlink:type="simple" xlink:role="mint"
                                 xlink:href="http://nomisma.org/id/seleuceia_ad_tigrim">Seleuceia ad Tigrim</nuds:geogname>
               </nuds:geographic>
            </nuds:typeDesc>
            <nuds:refDesc>
               <nuds:reference>ESM, p. 51</nuds:reference>
            </nuds:refDesc>
         </coin>
         <coin>
            <nuds:typeDesc>
               <nuds:dateRange>
                  <nuds:fromDate standardDate="-0305">305 B.C.</nuds:fromDate>
                  <nuds:toDate standardDate="-0281">281 B.C.</nuds:toDate>
               </nuds:dateRange>
               <nuds:denomination xlink:type="simple" xlink:href="http://nomisma.org/id/drachma">Drachma</nuds:denomination>
               <nuds:material xlink:type="simple" xlink:href="http://nomisma.org/id/ar">Silver</nuds:material>
               <nuds:authority>
                  <nuds:persname xlink:type="simple" xlink:role="authority"
                                 xlink:href="http://nomisma.org/id/seleucus_i">Seleucus I Nicator</nuds:persname>
               </nuds:authority>
               <nuds:geographic>
                  <nuds:geogname xlink:type="simple" xlink:role="mint"
                                 xlink:href="http://nomisma.org/id/seleuceia_ad_tigrim">Seleuceia ad Tigrim</nuds:geogname>
               </nuds:geographic>
            </nuds:typeDesc>
            <nuds:refDesc>
               <nuds:reference>ESM 42</nuds:reference>
            </nuds:refDesc>
         </coin>
         <coin>
            <nuds:typeDesc>
               <nuds:denomination xlink:type="simple" xlink:href="http://nomisma.org/id/drachma">Drachma</nuds:denomination>
               <nuds:material xlink:type="simple" xlink:href="http://nomisma.org/id/ar">Silver</nuds:material>
               <nuds:authority>
                  <nuds:persname xlink:type="simple" xlink:role="authority"
                                 xlink:href="http://nomisma.org/id/antiochus_i">Antiochus I Soter</nuds:persname>
                  <nuds:persname xlink:type="simple" xlink:role="authority"
                                 xlink:href="http://nomisma.org/id/antiochus_ii">Antiochus II Theos</nuds:persname>
                  <nuds:persname xlink:type="simple" xlink:role="authority"
                                 xlink:href="http://nomisma.org/id/seleucus_ii">Seleucus II Callinicus</nuds:persname>
               </nuds:authority>
               <nuds:geographic>
                  <nuds:geogname xlink:type="simple" xlink:role="mint"
                                 xlink:href="http://nomisma.org/id/laodiceia_ad_mare">Laodicea ad Mare</nuds:geogname>
               </nuds:geographic>
            </nuds:typeDesc>
            <nuds:refDesc>
               <nuds:reference>WSM 1211</nuds:reference>
            </nuds:refDesc>
         </coin>
         <coin>
            <nuds:typeDesc>
               <nuds:dateRange>
                  <nuds:fromDate standardDate="-0261">261 B.C.</nuds:fromDate>
                  <nuds:toDate standardDate="-0246">246 B.C.</nuds:toDate>
               </nuds:dateRange>
               <nuds:denomination xlink:type="simple" xlink:href="http://nomisma.org/id/tetradrachm">Tetradrachm</nuds:denomination>
               <nuds:material xlink:type="simple" xlink:href="http://nomisma.org/id/ar">Silver</nuds:material>
               <nuds:authority>
                  <nuds:persname xlink:type="simple" xlink:role="authority"
                                 xlink:href="http://nomisma.org/id/antiochus_ii">Antiochus II Theos</nuds:persname>
               </nuds:authority>
               <nuds:geographic>
                  <nuds:geogname xlink:type="simple" xlink:role="mint"
                                 xlink:href="http://nomisma.org/id/seleuceia_ad_tigrim">Seleuceia ad Tigrim</nuds:geogname>
               </nuds:geographic>
            </nuds:typeDesc>
            <nuds:refDesc>
               <nuds:reference>ESM 361</nuds:reference>
            </nuds:refDesc>
         </coin>
         <coin>
            <nuds:typeDesc>
               <nuds:denomination xlink:type="simple" xlink:href="http://nomisma.org/id/tetradrachm">Tetradrachm</nuds:denomination>
               <nuds:material xlink:type="simple" xlink:href="http://nomisma.org/id/ar">Silver</nuds:material>
               <nuds:authority>
                  <nuds:persname xlink:type="simple" xlink:role="authority"
                                 xlink:href="http://nomisma.org/id/antiochus_ii">Antiochus II Theos</nuds:persname>
               </nuds:authority>
               <nuds:geographic>
                  <nuds:geogname xlink:type="simple" xlink:role="mint"
                                 xlink:href="http://nomisma.org/id/seleuceia_ad_tigrim">Seleuceia ad Tigrim</nuds:geogname>
               </nuds:geographic>
            </nuds:typeDesc>
            <nuds:refDesc>
               <nuds:reference>Susa p. 76</nuds:reference>
            </nuds:refDesc>
         </coin>
         <coin>
            <nuds:typeDesc>
               <nuds:dateRange>
                  <nuds:fromDate standardDate="-0246">246 B.C.</nuds:fromDate>
                  <nuds:toDate standardDate="-0225">225 B.C.</nuds:toDate>
               </nuds:dateRange>
               <nuds:denomination xlink:type="simple" xlink:href="http://nomisma.org/id/drachma">Drachma</nuds:denomination>
               <nuds:material xlink:type="simple" xlink:href="http://nomisma.org/id/ar">Silver</nuds:material>
               <nuds:authority>
                  <nuds:persname xlink:type="simple" xlink:role="authority"
                                 xlink:href="http://nomisma.org/id/seleucus_ii">Seleucus II Callinicus</nuds:persname>
               </nuds:authority>
               <nuds:geographic>
                  <nuds:geogname xlink:type="simple" xlink:role="mint" xlink:href="http://nomisma.org/id/sardes">Sardis</nuds:geogname>
               </nuds:geographic>
            </nuds:typeDesc>
            <nuds:refDesc>
               <nuds:reference>WSM 1420</nuds:reference>
            </nuds:refDesc>
         </coin>
         <coin>
            <nuds:typeDesc>
               <nuds:dateRange>
                  <nuds:fromDate standardDate="-0246">246 B.C.</nuds:fromDate>
                  <nuds:toDate standardDate="-0225">225 B.C.</nuds:toDate>
               </nuds:dateRange>
               <nuds:denomination xlink:type="simple" xlink:href="http://nomisma.org/id/drachma">Drachma</nuds:denomination>
               <nuds:material xlink:type="simple" xlink:href="http://nomisma.org/id/ar">Silver</nuds:material>
               <nuds:authority>
                  <nuds:persname xlink:type="simple" xlink:role="authority"
                                 xlink:href="http://nomisma.org/id/seleucus_ii">Seleucus II Callinicus</nuds:persname>
               </nuds:authority>
               <nuds:geographic>
                  <nuds:geogname xlink:type="simple" xlink:role="mint" xlink:href="http://nomisma.org/id/sardes">Sardis</nuds:geogname>
               </nuds:geographic>
            </nuds:typeDesc>
            <nuds:refDesc>
               <nuds:reference>WSM 1422d</nuds:reference>
            </nuds:refDesc>
         </coin>
         <coin>
            <nuds:typeDesc>
               <nuds:dateRange>
                  <nuds:fromDate standardDate="-0246">246 B.C.</nuds:fromDate>
                  <nuds:toDate standardDate="-0225">225 B.C.</nuds:toDate>
               </nuds:dateRange>
               <nuds:denomination xlink:type="simple" xlink:href="http://nomisma.org/id/drachma">Drachma</nuds:denomination>
               <nuds:material xlink:type="simple" xlink:href="http://nomisma.org/id/ar">Silver</nuds:material>
               <nuds:authority>
                  <nuds:persname xlink:type="simple" xlink:role="authority"
                                 xlink:href="http://nomisma.org/id/seleucus_ii">Seleucus II Callinicus</nuds:persname>
               </nuds:authority>
               <nuds:geographic>
                  <nuds:geogname xlink:type="simple" xlink:role="mint" xlink:href="http://nomisma.org/id/sardes">Sardis</nuds:geogname>
               </nuds:geographic>
            </nuds:typeDesc>
            <nuds:refDesc>
               <nuds:reference>WSM 1422e</nuds:reference>
            </nuds:refDesc>
         </coin>
         <coin>
            <nuds:typeDesc>
               <nuds:dateRange>
                  <nuds:fromDate standardDate="-0246">246 B.C.</nuds:fromDate>
                  <nuds:toDate standardDate="-0225">225 B.C.</nuds:toDate>
               </nuds:dateRange>
               <nuds:denomination xlink:type="simple" xlink:href="http://nomisma.org/id/drachma">Drachma</nuds:denomination>
               <nuds:material xlink:type="simple" xlink:href="http://nomisma.org/id/ar">Silver</nuds:material>
               <nuds:authority>
                  <nuds:persname xlink:type="simple" xlink:role="authority"
                                 xlink:href="http://nomisma.org/id/seleucus_ii">Seleucus II Callinicus</nuds:persname>
               </nuds:authority>
               <nuds:geographic>
                  <nuds:geogname xlink:type="simple" xlink:role="mint" xlink:href="http://nomisma.org/id/sardes">Sardis</nuds:geogname>
               </nuds:geographic>
            </nuds:typeDesc>
            <nuds:refDesc>
               <nuds:reference>illegible</nuds:reference>
            </nuds:refDesc>
         </coin>
         <coin>
            <nuds:typeDesc>
               <nuds:dateRange>
                  <nuds:fromDate standardDate="-0323">323 B.C.</nuds:fromDate>
                  <nuds:toDate standardDate="-0283">283 B.C.</nuds:toDate>
               </nuds:dateRange>
               <nuds:denomination xlink:type="simple" xlink:href="http://nomisma.org/id/tetradrachm">Tetradrachm</nuds:denomination>
               <nuds:material xlink:type="simple" xlink:href="http://nomisma.org/id/ar">Silver</nuds:material>
               <nuds:authority>
                  <nuds:persname xlink:type="simple" xlink:role="authority"
                                 xlink:href="http://nomisma.org/id/ptolemy_i">Ptolemy I Soter</nuds:persname>
               </nuds:authority>
            </nuds:typeDesc>
         </coin>
         <coinGrp count="10">
            <nuds:typeDesc>
               <nuds:dateRange>
                  <nuds:fromDate standardDate="-0285">285 B.C.</nuds:fromDate>
                  <nuds:toDate standardDate="-0246">246 B.C.</nuds:toDate>
               </nuds:dateRange>
               <nuds:denomination xlink:type="simple" xlink:href="http://nomisma.org/id/tetradrachm">Tetradrachm</nuds:denomination>
               <nuds:material xlink:type="simple" xlink:href="http://nomisma.org/id/ar">Silver</nuds:material>
               <nuds:authority>
                  <nuds:persname xlink:type="simple" xlink:role="authority"
                                 xlink:href="http://nomisma.org/id/ptolemy_ii">Ptolemy II Philadelphus</nuds:persname>
               </nuds:authority>
            </nuds:typeDesc>
         </coinGrp>
         <coinGrp count="4">
            <nuds:typeDesc>
               <nuds:dateRange>
                  <nuds:fromDate standardDate="-0246">246 B.C.</nuds:fromDate>
                  <nuds:toDate standardDate="-0222">222 B.C.</nuds:toDate>
               </nuds:dateRange>
               <nuds:denomination xlink:type="simple" xlink:href="http://nomisma.org/id/tetradrachm">Tetradrachm</nuds:denomination>
               <nuds:material xlink:type="simple" xlink:href="http://nomisma.org/id/ar">Silver</nuds:material>
               <nuds:authority>
                  <nuds:persname xlink:type="simple" xlink:role="authority"
                                 xlink:href="http://nomisma.org/id/ptolemy_iii">Ptolemy III Euergetes</nuds:persname>
               </nuds:authority>
            </nuds:typeDesc>
         </coinGrp>
         <coinGrp count="3">
            <nuds:typeDesc>
               <nuds:material xlink:type="simple" xlink:href="http://nomisma.org/id/ar">Silver</nuds:material>
            </nuds:typeDesc>
         </coinGrp>
      </contents>
   </contentsDesc>
   <refDesc>
      <reference>Svoronos, JIAN 1899, pp. 289-96; 1907, pp. 3546, illus.; Athènes, pl. 28</reference>
      <reference>Newell, ESM and WSM indexes of hoards;  ESM p. 76, note 104 (burial date)</reference>
      <reference>Noe, ANSMN 10 (1962), p. 34</reference>
      <reference>Hackens, Antidorum W. Peremans, pp. 71-2</reference>
   </refDesc>
</nudsHoard>