<?xml version="1.0" encoding="UTF-8"?>
<nudsHoard xmlns="http://nomisma.org/nudsHoard" xmlns:mods="http://www.loc.gov/mods/v3"
           xmlns:nuds="http://nomisma.org/nuds"
           xmlns:gml="http://www.opengis.net/gml"
           xmlns:xsi="http://www.w3.org/2001/XMLSchema-instance"
           xmlns:xlink="http://www.w3.org/1999/xlink">
   <control>
      <recordId>igch1730</recordId>
      <maintenanceStatus>derived</maintenanceStatus>
      <publicationStatus>approved</publicationStatus>
      <maintenanceAgency>
         <agencyName>American Numismatic Society</agencyName>
      </maintenanceAgency>
      <maintenanceHistory>
         <maintenanceEvent>
            <eventType>derived</eventType>
            <eventDateTime standardDateTime="2020-04-17T19:38:26-04:00">Fri, 17 Apr 2020 19:38:26 -0400</eventDateTime>
            <agentType>human</agentType>
            <agent>Ethan Gruber</agent>
            <eventDescription>NUDS-Hoard records generated by Ethan Gruber from spreadsheets Disnarda Pinilla cleaned from the IGCH records.s</eventDescription>
         </maintenanceEvent>
      </maintenanceHistory>
      <rightsStmt>
         <copyrightHolder>American Numismatic Society</copyrightHolder>
         <license>http://opendatacommons.org/licenses/odbl/</license>
      </rightsStmt>
   </control>
   <descMeta>
      <title xml:lang="en">IGCH 1730</title>
      <subjectSet>
         <subject localType="period" xlink:type="simple"
                  xlink:href="http://nomisma.org/id/hellenistic_greece">Hellenistic Period</subject>
      </subjectSet>
      <hoardDesc>
         <findspot>
            <description xml:lang="en">Karnak, near Luxor</description>
            <fallsWithin>
               <gml:location>
                  <gml:Point>
                     <gml:coordinates>32.65393,25.71771</gml:coordinates>
                  </gml:Point>
               </gml:location>
               <geogname xlink:type="simple" xlink:role="findspot"
                         xlink:href="https://sws.geonames.org/360964/">Al Karnak (Egypt)</geogname>
               <geogname xlink:type="simple" xlink:role="ancient_place"
                         xlink:href="https://pleiades.stoa.org/places/786050">Karnak</geogname>
               <type xlink:type="simple" xlink:href="http://vocab.getty.edu/aat/300008347">inhabited places</type>
            </fallsWithin>
         </findspot>
         <deposit>
            <dateRange>
               <fromDate standardDate="-0300">300 B.C.</fromDate>
               <toDate standardDate="-0001">1 B.C.</toDate>
            </dateRange>
         </deposit>
         <discovery>
            <dateRange>
               <fromDate standardDate="1924">1924</fromDate>
               <toDate standardDate="1925">1925</toDate>
            </dateRange>
         </discovery>
         <disposition>
            <description xml:lang="en">unknown</description>
         </disposition>
      </hoardDesc>
      <contentsDesc>
         <contents>
            <description xml:lang="en">AE. In two vases from excavations at S. facade of VIIIth pylon: Uncertain count noted in IGCH including 1 [uncertain], which has been counted as 1. Then, the total count comes to 1 coin of a group of at least 2+ coins</description>
            <coinGrp certainty="http://nomisma.org/id/uncertain_value">
               <nuds:typeDesc>
                  <nuds:material xlink:type="simple" xlink:href="http://nomisma.org/id/ae">Bronze</nuds:material>
                  <nuds:authority>
                     <nuds:corpname xlink:type="simple" xlink:role="authority"
                                    xlink:href="http://nomisma.org/id/ptolemaic_empire">Ptolemaic Empire</nuds:corpname>
                     <nuds:famname xlink:type="simple" xlink:role="authority"
                                   xlink:href="http://nomisma.org/id/ptolemaic_dynasty">Ptolemaic Dynasty</nuds:famname>
                  </nuds:authority>
               </nuds:typeDesc>
            </coinGrp>
         </contents>
      </contentsDesc>
      <refDesc>
         <reference>ASA 1925, p. 13 (no details)</reference>
      </refDesc>
   </descMeta>
</nudsHoard>