<nudsHoard xmlns="http://nomisma.org/nudsHoard" xmlns:mods="http://www.loc.gov/mods/v3" xmlns:nuds="http://nomisma.org/nuds" xmlns:gml="http://www.opengis.net/gml" xmlns:xsi="http://www.w3.org/2001/XMLSchema-instance" xmlns:xlink="http://www.w3.org/1999/xlink">
    <control>
        <recordId>igch2007</recordId>
        <maintenanceStatus>derived</maintenanceStatus>
        <publicationStatus>approved</publicationStatus>
        <maintenanceAgency>
            <agencyName>American Numismatic Society</agencyName>
        </maintenanceAgency>
        <maintenanceHistory>
            <maintenanceEvent>
                <eventType>derived</eventType>
                <eventDateTime standardDateTime="2020-04-17T19:39:14-04:00">Fri, 17 Apr 2020 19:39:14 -0400</eventDateTime>
                <agentType>human</agentType>
                <agent>Ethan Gruber</agent>
                <eventDescription>NUDS-Hoard records generated by Ethan Gruber from spreadsheets Disnarda Pinilla cleaned from the IGCH records.s</eventDescription>
            </maintenanceEvent>
        </maintenanceHistory>
        <rightsStmt>
            <copyrightHolder>American Numismatic Society</copyrightHolder>
            <license>http://opendatacommons.org/licenses/odbl/</license>
        </rightsStmt>
    </control>
    <descMeta>
        <title xml:lang="en">IGCH 2007</title>
        <subjectSet>
            <subject localType="period" xlink:type="simple" xlink:href="http://nomisma.org/id/hellenistic_greece">Hellenistic Period</subject>
        </subjectSet>
        <hoardDesc>
            <findspot>
                <description xml:lang="en">Fasano, 50 km. NW of Brindisi, Apulia</description>
                <fallsWithin>
                    <gml:location>
                        <gml:Point>
                            <gml:coordinates>17.36007,40.83625</gml:coordinates>
                        </gml:Point>
                    </gml:location>
                    <geogname xlink:type="simple" xlink:role="findspot" xlink:href="https://sws.geonames.org/3177171/">Fasano (Italy)</geogname>
                    <type xlink:type="simple" xlink:href="http://vocab.getty.edu/aat/300008347">inhabited places</type>
                </fallsWithin>
            </findspot>
            <deposit>
                <date standardDate="-0228">228 B.C.</date>
            </deposit>
            <discovery>
                <date standardDate="1934">1934</date>
            </discovery>
            <disposition>
                <description xml:lang="en">Taranto 179</description>
            </disposition>
        </hoardDesc>
        <contentsDesc>
            <contents minCount="179">
                <description xml:lang="en">179+ AR</description>
                <coin>
                    <nuds:typeDesc>
                        <nuds:denomination xlink:type="simple" xlink:href="http://nomisma.org/id/stater">Stater</nuds:denomination>
                        <nuds:material xlink:type="simple" xlink:href="http://nomisma.org/id/ar">Silver</nuds:material>
                        <nuds:geographic>
                            <nuds:geogname xlink:type="simple" xlink:role="mint" xlink:href="http://nomisma.org/id/taras">Taras</nuds:geogname>
                        </nuds:geographic>
                    </nuds:typeDesc>
                    <nuds:refDesc>
                        <nuds:reference>Per. III</nuds:reference>
                    </nuds:refDesc>
                </coin>
                <coinGrp count="8">
                    <nuds:typeDesc>
                        <nuds:denomination xlink:type="simple" xlink:href="http://nomisma.org/id/stater">Stater</nuds:denomination>
                        <nuds:material xlink:type="simple" xlink:href="http://nomisma.org/id/ar">Silver</nuds:material>
                        <nuds:geographic>
                            <nuds:geogname xlink:type="simple" xlink:role="mint" xlink:href="http://nomisma.org/id/taras">Taras</nuds:geogname>
                        </nuds:geographic>
                    </nuds:typeDesc>
                    <nuds:refDesc>
                        <nuds:reference>Per. VII</nuds:reference>
                    </nuds:refDesc>
                </coinGrp>
                <coinGrp count="148">
                    <nuds:typeDesc>
                        <nuds:denomination xlink:type="simple" xlink:href="http://nomisma.org/id/stater">Stater</nuds:denomination>
                        <nuds:material xlink:type="simple" xlink:href="http://nomisma.org/id/ar">Silver</nuds:material>
                        <nuds:geographic>
                            <nuds:geogname xlink:type="simple" xlink:role="mint" xlink:href="http://nomisma.org/id/taras">Taras</nuds:geogname>
                        </nuds:geographic>
                    </nuds:typeDesc>
                    <nuds:refDesc>
                        <nuds:reference>Per. VIII</nuds:reference>
                    </nuds:refDesc>
                </coinGrp>
                <coinGrp count="21">
                    <nuds:typeDesc>
                        <nuds:denomination xlink:type="simple" xlink:href="http://nomisma.org/id/stater">Stater</nuds:denomination>
                        <nuds:material xlink:type="simple" xlink:href="http://nomisma.org/id/ar">Silver</nuds:material>
                        <nuds:geographic>
                            <nuds:geogname xlink:type="simple" xlink:role="mint" xlink:href="http://nomisma.org/id/taras">Taras</nuds:geogname>
                        </nuds:geographic>
                    </nuds:typeDesc>
                    <nuds:refDesc>
                        <nuds:reference>Per. IX</nuds:reference>
                    </nuds:refDesc>
                </coinGrp>
                <coin>
                    <nuds:typeDesc>
                        <nuds:denomination xlink:type="simple" xlink:href="http://nomisma.org/id/stater">Stater</nuds:denomination>
                        <nuds:material xlink:type="simple" xlink:href="http://nomisma.org/id/ar">Silver</nuds:material>
                        <nuds:geographic>
                            <nuds:geogname xlink:type="simple" xlink:role="mint" xlink:href="http://nomisma.org/id/thurium">Thurium</nuds:geogname>
                        </nuds:geographic>
                    </nuds:typeDesc>
                </coin>
            </contents>
        </contentsDesc>
        <refDesc>
            <reference>Breglia, AttiMemIIN 8 (1934), pp. 33-55, illus.</reference>
        </refDesc>
    </descMeta>
</nudsHoard>